LICENSE
MANIFEST.in
README.rst
setup.py
pygeppetto_django.egg-info/PKG-INFO
pygeppetto_django.egg-info/SOURCES.txt
pygeppetto_django.egg-info/dependency_links.txt
pygeppetto_django.egg-info/requires.txt
pygeppetto_django.egg-info/top_level.txt
pygeppetto_server/__init__.py
pygeppetto_server/admin.py
pygeppetto_server/apps.py
pygeppetto_server/consumers.py
pygeppetto_server/models.py
pygeppetto_server/routing.py
pygeppetto_server/tests.py
pygeppetto_server/urls.py
pygeppetto_server/views.py
pygeppetto_server/migrations/__init__.py